README.md
setup.py
Flask_Atomic_Auth.egg-info/PKG-INFO
Flask_Atomic_Auth.egg-info/SOURCES.txt
Flask_Atomic_Auth.egg-info/dependency_links.txt
Flask_Atomic_Auth.egg-info/entry_points.txt
Flask_Atomic_Auth.egg-info/not-zip-safe
Flask_Atomic_Auth.egg-info/requires.txt
Flask_Atomic_Auth.egg-info/top_level.txt
flask_atomic_auth/__init__.py
flask_atomic_auth/dao.py
flask_atomic_auth/decorators.py
flask_atomic_auth/dynamo.py
flask_atomic_auth/exceptions.py
flask_atomic_auth/routes.py