Metadata-Version: 2.1
Name: Flask-Atomic-Auth
Version: 0.0.2
Summary: User authorisation module for Flask projects.
Home-page: https://github.com/kmjbyrne/flask-atomic-auth
Author: Keith Byrne
Author-email: keithmbyrne@gmail.com
License: MIT
Keywords: python library utilities
Platform: UNKNOWN
Classifier: Development Status :: 3 - Alpha
Classifier: License :: OSI Approved :: MIT License
Classifier: Programming Language :: Python :: 3.7
